mirabest_identifier/__init__.py
mirabest_identifier/cli.py
mirabest_identifier/gradio_app.py
mirabest_identifier/inference.py
mirabest_identifier-0.1.0.dist-info/WHEEL
mirabest_identifier-0.1.0.dist-info/entry_points.txt
mirabest_identifier-0.1.0.dist-info/METADATA
mirabest_identifier-0.1.0.dist-info/RECORD
