Metadata-Version: 2.3
Name: mirabest-identifier
Version: 0.1.0
Summary: CLI and Gradio interface for classifying MiraBest radio galaxies
Author: Brian Welman
Author-email: Brian Welman <brianallisterwelman@gmail.com>
Requires-Dist: gradio>=3.36.1
Requires-Dist: pillow>=12.0.0
Requires-Dist: torch>=2.9.0
Requires-Dist: torchvision>=0.24.0
Requires-Dist: typer>=0.12.5
Requires-Python: >=3.12
